cyberbiz_sdk/__init__.py
cyberbiz_sdk/sdk.py
cyberbiz_sdk-0.2.0.dist-info/METADATA
cyberbiz_sdk-0.2.0.dist-info/WHEEL
cyberbiz_sdk-0.2.0.dist-info/RECORD
